pywirelessmbus/__init__.py
pywirelessmbus/devices/__init__.py
pywirelessmbus/devices/device.py
pywirelessmbus/devices/energy_cam.py
pywirelessmbus/devices/mock_device.py
pywirelessmbus/devices/weptech_oms.py
pywirelessmbus/exceptions/__init__.py
pywirelessmbus/exceptions/devices.py
pywirelessmbus/exceptions/general.py
pywirelessmbus/sticks/__init__.py
pywirelessmbus/sticks/im871a.py
pywirelessmbus/sticks/mock_stick.py
pywirelessmbus/utils/__init__.py
pywirelessmbus/utils/message.py
pywirelessmbus/utils/utils.py
pywirelessmbus/wmbus.py
pywirelessmbus-1.5.3.dist-info/LICENSE
pywirelessmbus-1.5.3.dist-info/WHEEL
pywirelessmbus-1.5.3.dist-info/METADATA
pywirelessmbus-1.5.3.dist-info/RECORD
