Metadata-Version: 2.1
Name: pywirelessmbus
Version: 1.5.3
Summary: A tool to receive and send Wireless-M-Bus messages.
Home-page: https://github.com/gewv-tu-dresden/pyWirelessMbus
License: MIT
Author: Karl Wolffgang
Author-email: karl_eugen.wolffgang@tu-dresden.de
Requires-Python: >=3.7,<4.0
Classifier: Development Status :: 3 - Alpha
Classifier: Intended Audience :: Developers
Classifier: License :: OSI Approved :: MIT License
Classifier: Operating System :: POSIX
Classifier: Operating System :: Unix
Classifier: Programming Language :: Python :: 3
Classifier: Programming Language :: Python :: 3.7
Classifier: Programming Language :: Python :: 3.8
Classifier: Programming Language :: Python :: 3.9
Classifier: Programming Language :: Python :: 3.10
Classifier: Programming Language :: Python :: 3.11
Classifier: Programming Language :: Python :: 3
Classifier: Programming Language :: Python :: 3.7
Requires-Dist: loguru (>=0.6.0,<0.7.0)
Requires-Dist: pyserial (>=3.5,<4.0)
Requires-Dist: pyserial-asyncio (>=0.6,<0.7)
